mielto/__init__.py
mielto/debug.py
mielto/exceptions.py
mielto/media.py
mielto/py.typed
mielto/agent/__init__.py
mielto/agent/agent.py
mielto/api/__init__.py
mielto/api/agent.py
mielto/api/api.py
mielto/api/evals.py
mielto/api/os.py
mielto/api/routes.py
mielto/api/settings.py
mielto/api/team.py
mielto/api/workflow.py
mielto/api/schemas/__init__.py
mielto/api/schemas/agent.py
mielto/api/schemas/evals.py
mielto/api/schemas/os.py
mielto/api/schemas/response.py
mielto/api/schemas/team.py
mielto/api/schemas/utils.py
mielto/api/schemas/workflows.py
mielto/cloud/aws/base.py
mielto/cloud/aws/s3/__init__.py
mielto/cloud/aws/s3/api_client.py
mielto/cloud/aws/s3/bucket.py
mielto/cloud/aws/s3/object.py
mielto/db/__init__.py
mielto/db/base.py
mielto/db/utils.py
mielto/db/dynamo/__init__.py
mielto/db/dynamo/dynamo.py
mielto/db/dynamo/schemas.py
mielto/db/dynamo/utils.py
mielto/db/firestore/__init__.py
mielto/db/firestore/firestore.py
mielto/db/firestore/schemas.py
mielto/db/firestore/utils.py
mielto/db/gcs_json/__init__.py
mielto/db/gcs_json/gcs_json_db.py
mielto/db/gcs_json/utils.py
mielto/db/in_memory/__init__.py
mielto/db/in_memory/in_memory_db.py
mielto/db/in_memory/utils.py
mielto/db/json/__init__.py
mielto/db/json/json_db.py
mielto/db/json/utils.py
mielto/db/migrations/__init__.py
mielto/db/migrations/v1_to_v2.py
mielto/db/mongo/__init__.py
mielto/db/mongo/mongo.py
mielto/db/mongo/schemas.py
mielto/db/mongo/utils.py
mielto/db/mysql/__init__.py
mielto/db/mysql/mysql.py
mielto/db/mysql/schemas.py
mielto/db/mysql/utils.py
mielto/db/postgres/__init__.py
mielto/db/postgres/postgres.py
mielto/db/postgres/schemas.py
mielto/db/postgres/utils.py
mielto/db/redis/__init__.py
mielto/db/redis/redis.py
mielto/db/redis/schemas.py
mielto/db/redis/utils.py
mielto/db/schemas/__init__.py
mielto/db/schemas/evals.py
mielto/db/schemas/knowledge.py
mielto/db/schemas/memory.py
mielto/db/schemas/metrics.py
mielto/db/singlestore/__init__.py
mielto/db/singlestore/schemas.py
mieltocore-0.0.21.dist-info/licenses/LICENSE
mieltocore-0.0.21.dist-info/METADATA
mieltocore-0.0.21.dist-info/WHEEL
mieltocore-0.0.21.dist-info/top_level.txt
mieltocore-0.0.21.dist-info/RECORD
