Metadata-Version: 2.4
Name: mieltocore
Version: 0.0.21
Summary: Mielto: a lightweight library for context aware AI applications
Author-email: Mielto <hi@mielto.com>
Project-URL: homepage, https://mielto.com
Project-URL: documentation, https://docs.mielto.com
Keywords: agent,reasoning,llm,large-language-model,framework
Classifier: Development Status :: 5 - Production/Stable
Classifier: Intended Audience :: Developers
Classifier: License :: OSI Approved :: Mozilla Public License 2.0 (MPL 2.0)
Classifier: Programming Language :: Python :: 3
Classifier: Programming Language :: Python :: 3.7
Classifier: Programming Language :: Python :: 3.8
Classifier: Programming Language :: Python :: 3.9
Classifier: Programming Language :: Python :: 3.10
Classifier: Programming Language :: Python :: 3.11
Classifier: Programming Language :: Python :: 3.12
Classifier: Operating System :: OS Independent
Classifier: Topic :: Scientific/Engineering :: Artificial Intelligence
Requires-Python: <4,>=3.7
License-File: LICENSE
Requires-Dist: docstring-parser
Requires-Dist: gitpython
Requires-Dist: httpx
Requires-Dist: packaging
Requires-Dist: pydantic-settings
Requires-Dist: pydantic
Requires-Dist: python-dotenv
Requires-Dist: python-multipart
Requires-Dist: pyyaml
Requires-Dist: rich
Requires-Dist: typer
Requires-Dist: typing-extensions
Provides-Extra: dev
Requires-Dist: mypy; extra == "dev"
Requires-Dist: pytest; extra == "dev"
Requires-Dist: pytest-asyncio; extra == "dev"
Requires-Dist: pytest-cov; extra == "dev"
Requires-Dist: pytest-mock; extra == "dev"
Requires-Dist: ruff; extra == "dev"
Requires-Dist: timeout-decorator; extra == "dev"
Requires-Dist: types-pyyaml; extra == "dev"
Requires-Dist: types-aiofiles; extra == "dev"
Requires-Dist: fastapi; extra == "dev"
Requires-Dist: uvicorn; extra == "dev"
Provides-Extra: os
Requires-Dist: fastapi; extra == "os"
Requires-Dist: uvicorn; extra == "os"
Provides-Extra: integration-tests
Requires-Dist: exa_py; extra == "integration-tests"
Requires-Dist: ddgs; extra == "integration-tests"
Requires-Dist: yfinance; extra == "integration-tests"
Requires-Dist: sqlalchemy; extra == "integration-tests"
Requires-Dist: Pillow; extra == "integration-tests"
Provides-Extra: opentelemetry
Requires-Dist: opentelemetry-sdk; extra == "opentelemetry"
Requires-Dist: opentelemetry-exporter-otlp; extra == "opentelemetry"
Provides-Extra: weave
Requires-Dist: weave; extra == "weave"
Provides-Extra: openlit
Requires-Dist: openlit; extra == "openlit"
Requires-Dist: mielto[opentelemetry]; extra == "openlit"
Provides-Extra: arize
Requires-Dist: arize-phoenix; extra == "arize"
Requires-Dist: mielto[opentelemetry]; extra == "arize"
Requires-Dist: opentelemetry-exporter-otlp-proto-grpc; extra == "arize"
Requires-Dist: opentelemetry-distro; extra == "arize"
Provides-Extra: langfuse
Requires-Dist: langfuse; extra == "langfuse"
Provides-Extra: aws-bedrock
Requires-Dist: boto3; extra == "aws-bedrock"
Requires-Dist: aioboto3; extra == "aws-bedrock"
Provides-Extra: anthropic
Requires-Dist: anthropic; extra == "anthropic"
Provides-Extra: azure
Requires-Dist: azure-ai-inference; extra == "azure"
Requires-Dist: aiohttp; extra == "azure"
Provides-Extra: cerebras
Requires-Dist: cerebras-cloud-sdk; extra == "cerebras"
Provides-Extra: cohere
Requires-Dist: cohere; extra == "cohere"
Provides-Extra: infinity
Requires-Dist: infinity_client; extra == "infinity"
Provides-Extra: google
Requires-Dist: google-genai; extra == "google"
Provides-Extra: groq
Requires-Dist: groq; extra == "groq"
Provides-Extra: ibm
Requires-Dist: ibm-watsonx-ai; extra == "ibm"
Provides-Extra: litellm
Requires-Dist: litellm; extra == "litellm"
Provides-Extra: lmstudio
Requires-Dist: lmstudio; extra == "lmstudio"
Provides-Extra: meta
Requires-Dist: llama-api-client; extra == "meta"
Provides-Extra: mistral
Requires-Dist: mistralai; extra == "mistral"
Provides-Extra: ollama
Requires-Dist: ollama; extra == "ollama"
Provides-Extra: openai
Requires-Dist: openai; extra == "openai"
Provides-Extra: portkey
Requires-Dist: portkey-ai; extra == "portkey"
Provides-Extra: agentql
Requires-Dist: agentql; extra == "agentql"
Provides-Extra: apify
Requires-Dist: apify-client; extra == "apify"
Provides-Extra: arxiv
Requires-Dist: arxiv; extra == "arxiv"
Provides-Extra: brave
Requires-Dist: brave-search; extra == "brave"
Provides-Extra: browserbase
Requires-Dist: browserbase; extra == "browserbase"
Requires-Dist: playwright; extra == "browserbase"
Provides-Extra: cartesia
Requires-Dist: cartesia; extra == "cartesia"
Provides-Extra: composio
Requires-Dist: composio; extra == "composio"
Provides-Extra: confluence
Requires-Dist: atlassian-python-api; extra == "confluence"
Provides-Extra: ddg
Requires-Dist: ddgs; extra == "ddg"
Provides-Extra: duckdb
Requires-Dist: duckdb; extra == "duckdb"
Provides-Extra: elevenlabs
Requires-Dist: elevenlabs; extra == "elevenlabs"
Provides-Extra: evm
Requires-Dist: web3; extra == "evm"
Provides-Extra: exa
Requires-Dist: exa_py; extra == "exa"
Provides-Extra: fal
Requires-Dist: fal_client; extra == "fal"
Provides-Extra: firecrawl
Requires-Dist: firecrawl-py; extra == "firecrawl"
Provides-Extra: crawl4ai
Requires-Dist: crawl4ai; extra == "crawl4ai"
Provides-Extra: github
Requires-Dist: PyGithub; extra == "github"
Provides-Extra: gmail
Requires-Dist: google-api-python-client; extra == "gmail"
Requires-Dist: google-auth-httplib2; extra == "gmail"
Requires-Dist: google-auth-oauthlib; extra == "gmail"
Provides-Extra: google-bigquery
Requires-Dist: google-cloud-bigquery; extra == "google-bigquery"
Provides-Extra: googlemaps
Requires-Dist: googlemaps; extra == "googlemaps"
Requires-Dist: google-maps-places; extra == "googlemaps"
Provides-Extra: matplotlib
Requires-Dist: matplotlib; extra == "matplotlib"
Provides-Extra: mcp
Requires-Dist: mcp; extra == "mcp"
Provides-Extra: mem0
Requires-Dist: mem0ai; extra == "mem0"
Provides-Extra: memori
Requires-Dist: memorisdk; extra == "memori"
Provides-Extra: newspaper
Requires-Dist: newspaper4k; extra == "newspaper"
Requires-Dist: lxml_html_clean; extra == "newspaper"
Provides-Extra: opencv
Requires-Dist: opencv-python; extra == "opencv"
Provides-Extra: psycopg
Requires-Dist: psycopg-binary; extra == "psycopg"
Requires-Dist: psycopg; extra == "psycopg"
Provides-Extra: todoist
Requires-Dist: todoist-api-python; extra == "todoist"
Provides-Extra: valyu
Requires-Dist: valyu; extra == "valyu"
Provides-Extra: webex
Requires-Dist: webexpythonsdk; extra == "webex"
Provides-Extra: yfinance
Requires-Dist: yfinance; extra == "yfinance"
Provides-Extra: youtube
Requires-Dist: youtube_transcript_api; extra == "youtube"
Provides-Extra: zep
Requires-Dist: zep-cloud; extra == "zep"
Provides-Extra: daytona
Requires-Dist: daytona; extra == "daytona"
Provides-Extra: oxylabs
Requires-Dist: oxylabs; extra == "oxylabs"
Provides-Extra: trafilatura
Requires-Dist: trafilatura; extra == "trafilatura"
Provides-Extra: neo4j
Requires-Dist: neo4j; extra == "neo4j"
Provides-Extra: sql
Requires-Dist: sqlalchemy; extra == "sql"
Provides-Extra: postgres
Requires-Dist: psycopg-binary; extra == "postgres"
Provides-Extra: sqlite
Requires-Dist: sqlalchemy; extra == "sqlite"
Provides-Extra: gcs
Requires-Dist: google-cloud-storage; extra == "gcs"
Provides-Extra: firestore
Requires-Dist: google-cloud-firestore; extra == "firestore"
Provides-Extra: redis
Requires-Dist: redis; extra == "redis"
Provides-Extra: pgvector
Requires-Dist: pgvector; extra == "pgvector"
Provides-Extra: chromadb
Requires-Dist: chromadb; extra == "chromadb"
Provides-Extra: lancedb
Requires-Dist: lancedb>=0.24.0; extra == "lancedb"
Requires-Dist: tantivy; extra == "lancedb"
Provides-Extra: pylance
Requires-Dist: pylance; extra == "pylance"
Provides-Extra: qdrant
Requires-Dist: qdrant-client; extra == "qdrant"
Provides-Extra: couchbase
Requires-Dist: couchbase; extra == "couchbase"
Provides-Extra: cassandra
Requires-Dist: cassio; extra == "cassandra"
Provides-Extra: mongodb
Requires-Dist: pymongo[srv]; extra == "mongodb"
Provides-Extra: singlestore
Requires-Dist: sqlalchemy; extra == "singlestore"
Provides-Extra: weaviate
Requires-Dist: weaviate-client; extra == "weaviate"
Provides-Extra: milvusdb
Requires-Dist: pymilvus>=2.5.10; extra == "milvusdb"
Provides-Extra: clickhouse
Requires-Dist: clickhouse-connect; extra == "clickhouse"
Provides-Extra: pinecone
Requires-Dist: pinecone==5.4.2; extra == "pinecone"
Provides-Extra: surrealdb
Requires-Dist: surrealdb>=1.0.4; extra == "surrealdb"
Provides-Extra: upstash
Requires-Dist: upstash-vector; extra == "upstash"
Provides-Extra: pdf
Requires-Dist: pypdf; extra == "pdf"
Requires-Dist: rapidocr_onnxruntime; extra == "pdf"
Provides-Extra: docx
Requires-Dist: python-docx; extra == "docx"
Provides-Extra: text
Requires-Dist: aiofiles; extra == "text"
Provides-Extra: csv
Requires-Dist: aiofiles; extra == "csv"
Provides-Extra: markdown
Requires-Dist: unstructured; extra == "markdown"
Requires-Dist: markdown; extra == "markdown"
Requires-Dist: aiofiles; extra == "markdown"
Provides-Extra: chonkie
Requires-Dist: chonkie[st]; extra == "chonkie"
Requires-Dist: chonkie; extra == "chonkie"
Provides-Extra: langchain
Requires-Dist: langchain-community; extra == "langchain"
Requires-Dist: langchain-docling; extra == "langchain"
Requires-Dist: langchain-core; extra == "langchain"
Requires-Dist: langchain; extra == "langchain"
Provides-Extra: agui
Requires-Dist: ag-ui-protocol; extra == "agui"
Provides-Extra: huggingface
Requires-Dist: huggingface-hub; extra == "huggingface"
Provides-Extra: performance
Requires-Dist: memory_profiler; extra == "performance"
Provides-Extra: cookbooks
Requires-Dist: inquirer; extra == "cookbooks"
Requires-Dist: email_validator; extra == "cookbooks"
Provides-Extra: docker
Requires-Dist: mielto-infra[docker]; extra == "docker"
Provides-Extra: aws
Requires-Dist: mielto-infra[aws]; extra == "aws"
Requires-Dist: mielto-infra[docker]; extra == "aws"
Provides-Extra: infra
Requires-Dist: mielto-infra; extra == "infra"
Provides-Extra: models
Requires-Dist: mielto[aws-bedrock]; extra == "models"
Requires-Dist: mielto[anthropic]; extra == "models"
Requires-Dist: mielto[azure]; extra == "models"
Requires-Dist: mielto[cerebras]; extra == "models"
Requires-Dist: mielto[cohere]; extra == "models"
Requires-Dist: mielto[infinity]; extra == "models"
Requires-Dist: mielto[google]; extra == "models"
Requires-Dist: mielto[groq]; extra == "models"
Requires-Dist: mielto[ibm]; extra == "models"
Requires-Dist: mielto[infinity]; extra == "models"
Requires-Dist: mielto[litellm]; extra == "models"
Requires-Dist: mielto[meta]; extra == "models"
Requires-Dist: mielto[mistral]; extra == "models"
Requires-Dist: mielto[ollama]; extra == "models"
Requires-Dist: mielto[openai]; extra == "models"
Requires-Dist: mielto[portkey]; extra == "models"
Provides-Extra: tools
Requires-Dist: mielto[apify]; extra == "tools"
Requires-Dist: mielto[arxiv]; extra == "tools"
Requires-Dist: mielto[brave]; extra == "tools"
Requires-Dist: mielto[exa]; extra == "tools"
Requires-Dist: mielto[cartesia]; extra == "tools"
Requires-Dist: mielto[ddg]; extra == "tools"
Requires-Dist: mielto[duckdb]; extra == "tools"
Requires-Dist: mielto[newspaper]; extra == "tools"
Requires-Dist: mielto[youtube]; extra == "tools"
Requires-Dist: mielto[firecrawl]; extra == "tools"
Requires-Dist: mielto[crawl4ai]; extra == "tools"
Requires-Dist: mielto[github]; extra == "tools"
Requires-Dist: mielto[gmail]; extra == "tools"
Requires-Dist: mielto[googlemaps]; extra == "tools"
Requires-Dist: mielto[todoist]; extra == "tools"
Requires-Dist: mielto[matplotlib]; extra == "tools"
Requires-Dist: mielto[elevenlabs]; extra == "tools"
Requires-Dist: mielto[evm]; extra == "tools"
Requires-Dist: mielto[fal]; extra == "tools"
Requires-Dist: mielto[webex]; extra == "tools"
Requires-Dist: mielto[mcp]; extra == "tools"
Requires-Dist: mielto[browserbase]; extra == "tools"
Requires-Dist: mielto[agentql]; extra == "tools"
Requires-Dist: mielto[opencv]; extra == "tools"
Requires-Dist: mielto[valyu]; extra == "tools"
Requires-Dist: mielto[confluence]; extra == "tools"
Requires-Dist: mielto[oxylabs]; extra == "tools"
Requires-Dist: mielto[zep]; extra == "tools"
Requires-Dist: mielto[mem0]; extra == "tools"
Requires-Dist: mielto[memori]; extra == "tools"
Requires-Dist: mielto[google_bigquery]; extra == "tools"
Requires-Dist: mielto[psycopg]; extra == "tools"
Requires-Dist: mielto[trafilatura]; extra == "tools"
Requires-Dist: mielto[neo4j]; extra == "tools"
Provides-Extra: storage
Requires-Dist: mielto[sql]; extra == "storage"
Requires-Dist: mielto[postgres]; extra == "storage"
Requires-Dist: mielto[sqlite]; extra == "storage"
Requires-Dist: mielto[gcs]; extra == "storage"
Requires-Dist: mielto[firestore]; extra == "storage"
Requires-Dist: mielto[redis]; extra == "storage"
Provides-Extra: vectordbs
Requires-Dist: mielto[pgvector]; extra == "vectordbs"
Requires-Dist: mielto[chromadb]; extra == "vectordbs"
Requires-Dist: mielto[lancedb]; extra == "vectordbs"
Requires-Dist: mielto[qdrant]; extra == "vectordbs"
Requires-Dist: mielto[couchbase]; extra == "vectordbs"
Requires-Dist: mielto[cassandra]; extra == "vectordbs"
Requires-Dist: mielto[mongodb]; extra == "vectordbs"
Requires-Dist: mielto[singlestore]; extra == "vectordbs"
Requires-Dist: mielto[weaviate]; extra == "vectordbs"
Requires-Dist: mielto[milvusdb]; extra == "vectordbs"
Requires-Dist: mielto[clickhouse]; extra == "vectordbs"
Requires-Dist: mielto[pinecone]; extra == "vectordbs"
Requires-Dist: mielto[surrealdb]; extra == "vectordbs"
Requires-Dist: mielto[upstash]; extra == "vectordbs"
Provides-Extra: knowledge
Requires-Dist: mielto[langchain]; extra == "knowledge"
Requires-Dist: mielto[pdf]; extra == "knowledge"
Requires-Dist: mielto[docx]; extra == "knowledge"
Requires-Dist: mielto[text]; extra == "knowledge"
Requires-Dist: mielto[csv]; extra == "knowledge"
Requires-Dist: mielto[markdown]; extra == "knowledge"
Requires-Dist: mielto[chonkie]; extra == "knowledge"
Provides-Extra: embedders
Requires-Dist: mielto[huggingface]; extra == "embedders"
Provides-Extra: tests
Requires-Dist: mielto[dev]; extra == "tests"
Requires-Dist: mielto[models]; extra == "tests"
Requires-Dist: mielto[tools]; extra == "tests"
Requires-Dist: mielto[storage]; extra == "tests"
Requires-Dist: mielto[vectordbs]; extra == "tests"
Requires-Dist: mielto[knowledge]; extra == "tests"
Requires-Dist: mielto[embedders]; extra == "tests"
Requires-Dist: mielto[performance]; extra == "tests"
Requires-Dist: mielto[cookbooks]; extra == "tests"
Requires-Dist: mielto[agui]; extra == "tests"
Requires-Dist: twine; extra == "tests"
Requires-Dist: build; extra == "tests"
Dynamic: license-file
